simular/__init__.py
simular/cli.py
simular-0.0.0.dist-info/DESCRIPTION.rst
simular-0.0.0.dist-info/METADATA
simular-0.0.0.dist-info/RECORD
simular-0.0.0.dist-info/WHEEL
simular-0.0.0.dist-info/entry_points.txt
simular-0.0.0.dist-info/metadata.json
simular-0.0.0.dist-info/top_level.txt
